{
	"name": "ProductsDataset",
	"properties": {
		"linkedServiceName": {
			"referenceName": "Linkedservice_storagedemoramm",
			"type": "LinkedServiceReference"
		},
		"annotations": [],
		"type": "DelimitedText",
		"typeProperties": {
			"location": {
				"type": "AzureBlobStorageLocation",
				"fileName": "Products.csv",
				"folderPath": "input",
				"container": "adfdemo"
			},
			"columnDelimiter": ",",
			"escapeChar": "\\",
			"firstRowAsHeader": true,
			"quoteChar": "\""
		},
		"schema": [
			{
				"name": "ProductID",
				"type": "String"
			},
			{
				"name": "ProductName",
				"type": "String"
			},
			{
				"name": "SupplierID",
				"type": "String"
			},
			{
				"name": "CategoryID",
				"type": "String"
			},
			{
				"name": "Unit",
				"type": "String"
			},
			{
				"name": "Price",
				"type": "String"
			}
		]
	},
	"type": "Microsoft.DataFactory/factories/datasets"
}